fastapi_extras/__init__.py
fastapi_extras/getters.py
fastapi_extras/handlers.py
fastapi_extras/py.typed
fastapi_extras/session/__init__.py
fastapi_extras/session/fs.py
fastapi_extras/session/memory.py
fastapi_extras3-0.3.0.dist-info/LICENSE
fastapi_extras3-0.3.0.dist-info/METADATA
fastapi_extras3-0.3.0.dist-info/WHEEL
fastapi_extras3-0.3.0.dist-info/top_level.txt
fastapi_extras3-0.3.0.dist-info/RECORD
