Metadata-Version: 2.1
Name: fastapi_extras3
Version: 0.3.0
Summary: Utilities to make using fastapi a little easier.
Author-email: Andrew Scott <imgurbot12@gmail.com>
License: The MIT License (MIT)
Project-URL: homepage, https://github.com/imgurbot12/fastapi-extras
Keywords: fastapi,utils,session,sync,dataclass
Classifier: Framework :: FastAPI
Classifier: Intended Audience :: Developers
Classifier: License :: OSI Approved :: MIT License
Classifier: Operating System :: OS Independent
Classifier: Programming Language :: Python :: 3
Classifier: Programming Language :: Python :: 3
Classifier: Programming Language :: Python :: 3.8
Classifier: Programming Language :: Python :: 3.9
Classifier: Programming Language :: Python :: 3.10
Classifier: Programming Language :: Python :: 3.11
Classifier: Programming Language :: Python :: 3.12
Requires-Python: >=3.8
License-File: LICENSE
Requires-Dist: fastapi >=0.115.5
